bsts/__init__.py
bsts/bsts.py
bsts/horseshoe.py
bsts/impact.py
bsts/min_max_scaler.py
bsts-0.1.dist-info/LICENSE
bsts-0.1.dist-info/METADATA
bsts-0.1.dist-info/WHEEL
bsts-0.1.dist-info/top_level.txt
bsts-0.1.dist-info/RECORD
