Metadata-Version: 2.1
Name: bsts
Version: 0.1
Summary: Python library for Bayesian structural time series
Home-page: UNKNOWN
Author: Bati Sengul
License: UNKNOWN
Platform: UNKNOWN
Classifier: Programming Language :: Python :: 3
Requires-Python: >=3.0
License-File: LICENSE
Requires-Dist: jax
Requires-Dist: numpyro
Requires-Dist: matplotlib
Requires-Dist: numpy
